tooltip/__init__.py
tooltip/main.py
tooltip-1.0.0.dist-info/LICENSE
tooltip-1.0.0.dist-info/METADATA
tooltip-1.0.0.dist-info/WHEEL
tooltip-1.0.0.dist-info/top_level.txt
tooltip-1.0.0.dist-info/RECORD
