Metadata-Version: 2.1
Name: tooltip
Version: 1.0.0
Summary: Uma descrição do seu pacote
Home-page: https://github.com/guisaldanha/tooltip
Author: Guilherme Saldanha
Author-email: guisaldanha@gmail.com
License: MIT
Keywords: dev,tooltip,python,package,tip,help
Classifier: Intended Audience :: Developers
Classifier: License :: Freely Distributable
Classifier: Operating System :: Microsoft :: Windows
Classifier: Operating System :: Unix
Classifier: Programming Language :: Python :: 3.11
Classifier: Topic :: Utilities
License-File: LICENSE
